README.txt
setup.py
docs/HISTORY.txt
eea/__init__.py
eea.faceted.blue.egg-info/PKG-INFO
eea.faceted.blue.egg-info/SOURCES.txt
eea.faceted.blue.egg-info/dependency_links.txt
eea.faceted.blue.egg-info/entry_points.txt
eea.faceted.blue.egg-info/namespace_packages.txt
eea.faceted.blue.egg-info/not-zip-safe
eea.faceted.blue.egg-info/requires.txt
eea.faceted.blue.egg-info/top_level.txt
eea/faceted/__init__.py
eea/faceted/blue/__init__.py
eea/faceted/blue/configure.zcml
eea/faceted/blue/profiles.zcml
eea/faceted/blue/version.txt
eea/faceted/blue/browser/__init__.py
eea/faceted/blue/browser/configure.zcml
eea/faceted/blue/browser/images/ajax-loader-small.gif
eea/faceted/blue/browser/images/ajax-loader.gif
eea/faceted/blue/browser/images/bottom-widgets.png
eea/faceted/blue/browser/images/bottomcenter-widgets.png
eea/faceted/blue/browser/images/center-widgets.png
eea/faceted/blue/browser/images/left-widgets.png
eea/faceted/blue/browser/images/right-widgets.png
eea/faceted/blue/browser/images/top-widgets.png
eea/faceted/blue/browser/images/ui-icons_222222_256x240-green.png
eea/faceted/blue/browser/stylesheets/edit.css
eea/faceted/blue/browser/stylesheets/js.css
eea/faceted/blue/browser/stylesheets/view.css
eea/faceted/blue/profiles/default/cssregistry.xml