Metadata-Version: 1.0
Name: eea.faceted.blue
Version: 1.0
Summary: UNKNOWN
Home-page: http://svn.plone.org/svn/collective/
Author: David Batranu
Author-email: david@eaudeweb.ro
License: GPL
Keywords: eea facetednavigation blue theme
Platform: UNKNOWN
Classifier: Programming Language :: Python
